README.md
setup.py
pulumi_scaleway/__init__.py
pulumi_scaleway/_inputs.py
pulumi_scaleway/_utilities.py
pulumi_scaleway/account_ssh_key.py
pulumi_scaleway/apple_slicon_valley_server.py
pulumi_scaleway/baremetal_server.py
pulumi_scaleway/database.py
pulumi_scaleway/database_acl.py
pulumi_scaleway/database_instance.py
pulumi_scaleway/database_privilege.py
pulumi_scaleway/database_user.py
pulumi_scaleway/domain_record.py
pulumi_scaleway/get_account_ssh_key.py
pulumi_scaleway/get_baremetal_offer.py
pulumi_scaleway/get_database.py
pulumi_scaleway/get_database_acl.py
pulumi_scaleway/get_database_instance.py
pulumi_scaleway/get_database_privilege.py
pulumi_scaleway/get_domain_record.py
pulumi_scaleway/get_instance_image.py
pulumi_scaleway/get_instance_ip.py
pulumi_scaleway/get_instance_security_group.py
pulumi_scaleway/get_instance_server.py
pulumi_scaleway/get_instance_volume.py
pulumi_scaleway/get_kubernetes_cluster.py
pulumi_scaleway/get_kubernetes_node_pool.py
pulumi_scaleway/get_loadbalancer.py
pulumi_scaleway/get_loadbalancer_ip.py
pulumi_scaleway/get_marketplace_image.py
pulumi_scaleway/get_registry_image.py
pulumi_scaleway/get_registry_namespace.py
pulumi_scaleway/get_vpc_private_network.py
pulumi_scaleway/get_vpc_public_gateway.py
pulumi_scaleway/get_vpc_public_gateway_dhcp.py
pulumi_scaleway/get_vpc_public_gateway_ip.py
pulumi_scaleway/instance_ip.py
pulumi_scaleway/instance_ip_reverse_dns.py
pulumi_scaleway/instance_placement_group.py
pulumi_scaleway/instance_private_nic.py
pulumi_scaleway/instance_security_group.py
pulumi_scaleway/instance_security_group_rules.py
pulumi_scaleway/instance_server.py
pulumi_scaleway/instance_snapshot.py
pulumi_scaleway/instance_volume.py
pulumi_scaleway/iot_device.py
pulumi_scaleway/iot_hub.py
pulumi_scaleway/iot_network.py
pulumi_scaleway/iot_route.py
pulumi_scaleway/kubernetes_cluster.py
pulumi_scaleway/kubernetes_node_pool.py
pulumi_scaleway/loadbalancer.py
pulumi_scaleway/loadbalancer_backend.py
pulumi_scaleway.egg-info/PKG-INFO
pulumi_scaleway.egg-info/SOURCES.txt
pulumi_scaleway.egg-info/dependency_links.txt
pulumi_scaleway.egg-info/not-zip-safe
pulumi_scaleway.egg-info/requires.txt
pulumi_scaleway.egg-info/top_level.txt
