Metadata-Version: 2.1
Name: pulumi-scaleway
Version: 0.1.3
Summary: A Pulumi package for creating and managing scaleway cloud resources.
Home-page: https://leebriggs.co.uk/projects#pulumi-scaleway
License: Apache-2.0
Project-URL: Repository, https://github.com/jaxxstorm/pulumi-scaleway
Keywords: pulumi scaleway
Platform: UNKNOWN
